setup.py
HtBlowfishStorePlugin.egg-info/PKG-INFO
HtBlowfishStorePlugin.egg-info/SOURCES.txt
HtBlowfishStorePlugin.egg-info/dependency_links.txt
HtBlowfishStorePlugin.egg-info/entry_points.txt
HtBlowfishStorePlugin.egg-info/not-zip-safe
HtBlowfishStorePlugin.egg-info/requires.txt
HtBlowfishStorePlugin.egg-info/top_level.txt
htblowfishstore/__init__.py
htblowfishstore/htblowfishstore.py