Metadata-Version: 1.0
Name: HtBlowfishStorePlugin
Version: 0.1
Summary: HtPasswdStore for Trac's AccountManager with Blowfish support.
Home-page: http://mitar.tnode.com/
Author: Mitar
Author-email: mitar.trac@tnode.com
License: GPLv3
Keywords: trac plugin
Platform: UNKNOWN
